pyclesperanto_prototype/__init__.py
pyclesperanto_prototype/_bia_bob_plugins.py
pyclesperanto_prototype/_tier0/__init__.py
pyclesperanto_prototype/_tier0/_array_operators.py
pyclesperanto_prototype/_tier0/_available_device_names.py
pyclesperanto_prototype/_tier0/_backends.py
pyclesperanto_prototype/_tier0/_categories.py
pyclesperanto_prototype/_tier0/_cl_image.py
pyclesperanto_prototype/_tier0/_cl_info.py
pyclesperanto_prototype/_tier0/_create.py
pyclesperanto_prototype/_tier0/_cuda_backend.py
pyclesperanto_prototype/_tier0/_cuda_execute.py
pyclesperanto_prototype/_tier0/_device.py
pyclesperanto_prototype/_tier0/_execute.py
pyclesperanto_prototype/_tier0/_opencl_backend.py
pyclesperanto_prototype/_tier0/_opencl_execute.py
pyclesperanto_prototype/_tier0/_operations.py
pyclesperanto_prototype/_tier0/_plugin_function.py
pyclesperanto_prototype/_tier0/_program.py
pyclesperanto_prototype/_tier0/_pull.py
pyclesperanto_prototype/_tier0/_push.py
pyclesperanto_prototype/_tier0/_pycl.py
pyclesperanto_prototype/_tier0/_radius_to_kernel_size.py
pyclesperanto_prototype/_tier0/_set_wait_for_kernel_finish.py
pyclesperanto_prototype/_tier0/_sigma_to_kernel_size.py
pyclesperanto_prototype/_tier0/_types.py
pyclesperanto_prototype/_tier0/preamble.cl
pyclesperanto_prototype/_tier1/__init__.py
pyclesperanto_prototype/_tier1/_absolute.py
pyclesperanto_prototype/_tier1/_add_image_and_scalar.py
pyclesperanto_prototype/_tier1/_add_images_weighted.py
pyclesperanto_prototype/_tier1/_average_distance_of_n_far_off_distances.py
pyclesperanto_prototype/_tier1/_average_distance_of_n_nearest_distances.py
pyclesperanto_prototype/_tier1/_average_distance_of_n_shortest_distances.py
pyclesperanto_prototype/_tier1/_average_distance_of_touching_neighbors.py
pyclesperanto_prototype/_tier1/_binary_and.py
pyclesperanto_prototype/_tier1/_binary_edge_detection.py
pyclesperanto_prototype/_tier1/_binary_not.py
pyclesperanto_prototype/_tier1/_binary_or.py
pyclesperanto_prototype/_tier1/_binary_subtract.py
pyclesperanto_prototype-0.24.5.dist-info/LICENSE
pyclesperanto_prototype-0.24.5.dist-info/METADATA
pyclesperanto_prototype-0.24.5.dist-info/WHEEL
pyclesperanto_prototype-0.24.5.dist-info/entry_points.txt
pyclesperanto_prototype-0.24.5.dist-info/top_level.txt
pyclesperanto_prototype-0.24.5.dist-info/RECORD
