Metadata-Version: 2.1
Name: pyclesperanto_prototype
Version: 0.24.5
Summary: GPU-accelerated image processing in python using OpenCL
Home-page: https://github.com/clEsperanto/pyclesperanto_prototype
Author: Robert Haase
Author-email: robert.haase@uni-leipzig.de
License: BSD-3-Clause
Project-URL: Bug Tracker, https://github.com/clEsperanto/pyclesperanto_prototype/issues
Project-URL: Documentation, https://github.com/clEsperanto/pyclesperanto_prototype#README.md
Project-URL: Source Code, https://github.com/clEsperanto/pyclesperanto_prototype
Project-URL: User Support, https://github.com/clEsperanto/pyclesperanto_prototype/issues
Classifier: Development Status :: 3 - Alpha
Classifier: Intended Audience :: Science/Research
Classifier: Intended Audience :: Developers
Classifier: Topic :: Scientific/Engineering :: Image Processing
Classifier: Topic :: Scientific/Engineering :: Information Analysis
Classifier: Programming Language :: Python
Classifier: Programming Language :: Python :: 3
Classifier: Programming Language :: Python :: 3.7
Classifier: Programming Language :: Python :: 3.8
Classifier: Programming Language :: Python :: 3.9
Classifier: Programming Language :: Python :: 3.10
Classifier: Operating System :: OS Independent
Classifier: License :: OSI Approved :: BSD License
Requires-Python: >=3.6
License-File: LICENSE
Requires-Dist: numpy!=1.19.4,<2.0.0
Requires-Dist: pyopencl
Requires-Dist: toolz
Requires-Dist: scikit-image!=0.20.0,>=0.18.0
Requires-Dist: matplotlib
Requires-Dist: transforms3d
